streamlit_video_editor/__init__.py
streamlit_video_editor/_version.py
streamlit_video_editor-0.0.6.dist-info/licenses/LICENSE
streamlit_video_editor-0.0.6.dist-info/METADATA
streamlit_video_editor-0.0.6.dist-info/WHEEL
streamlit_video_editor-0.0.6.dist-info/top_level.txt
streamlit_video_editor-0.0.6.dist-info/RECORD
