Metadata-Version: 2.4
Name: streamlit-video-editor
Version: 0.0.6
Summary: A Streamlit custom component to display a simple video editor.
Home-page: https://github.com/antunsz/streamlit-video-editor
Author: Carlos André Antunes
Author-email: 
Project-URL: Github, https://github.com/antunsz/streamlit-video-editor
Classifier: Programming Language :: Python :: 3
Classifier: Operating System :: OS Independent
Requires-Python: >=3.6
License-File: LICENSE
Requires-Dist: streamlit>=0.70
Dynamic: author
Dynamic: classifier
Dynamic: description
Dynamic: description-content-type
Dynamic: home-page
Dynamic: license-file
Dynamic: project-url
Dynamic: requires-dist
Dynamic: requires-python
Dynamic: summary
